LICENSE
MANIFEST.in
README.md
setup.py
ellipticcurve/__init__.py
ellipticcurve/curve.py
ellipticcurve/ecdsa.py
ellipticcurve/math.py
ellipticcurve/point.py
ellipticcurve/privateKey.py
ellipticcurve/publicKey.py
ellipticcurve/signature.py
ellipticcurve/utils/__init__.py
ellipticcurve/utils/binary.py
ellipticcurve/utils/compatibility.py
ellipticcurve/utils/der.py
ellipticcurve/utils/file.py
ellipticcurve/utils/integer.py
ellipticcurve/utils/oid.py
ellipticcurve/utils/pem.py
fabank_ecdsa.egg-info/PKG-INFO
fabank_ecdsa.egg-info/SOURCES.txt
fabank_ecdsa.egg-info/dependency_links.txt
fabank_ecdsa.egg-info/top_level.txt