Metadata-Version: 2.1
Name: fabank-ecdsa
Version: 1.0.1
Summary: A lightweight and fast pure python ECDSA library
Home-page: https://github.com/fabankbr/ecdsa-python.git
Author: Fabank
Author-email: infra@fabank.com.br
License: MIT License
Keywords: ecdsa,elliptic curve,elliptic,curve,fabank,cryptograph,secp256k1,prime256v1
License-File: LICENSE
